pytest_mp/__init__.py
pytest_mp/junitxml.py
pytest_mp/plugin.py
pytest_mp/terminal.py
pytest_mp-0.0.4.dist-info/METADATA
pytest_mp-0.0.4.dist-info/RECORD
pytest_mp-0.0.4.dist-info/WHEEL
pytest_mp-0.0.4.dist-info/entry_points.txt
pytest_mp-0.0.4.dist-info/top_level.txt
